.checkignore
.coveragerc
.dockerignore
.jshintignore
.jshintrc
.travis-extra-install.sh
.travis-requirements-build.sh
.travis.yml
AUTHORS.rst
CHANGES.rst
COPYING
Dockerfile
INSTALL.rst
MANIFEST.in
Procfile
README.rst
babel.cfg
docker-compose.yml
elasticsearch.yml
pytest.ini
requirements.devel.txt
requirements.developer.txt
requirements.pinned.txt
requirements.prod.txt
requirements.qa.txt
requirements.topical.branches.txt
run-tests.sh
setup.cfg
setup.py
.github/ISSUE_TEMPLATE.md
CDS.egg-info/PKG-INFO
CDS.egg-info/SOURCES.txt
CDS.egg-info/dependency_links.txt
CDS.egg-info/entry_points.txt
CDS.egg-info/not-zip-safe
CDS.egg-info/requires.txt
CDS.egg-info/top_level.txt
benchmarks/anonymous.py
cds/__init__.py
cds/celery.py
cds/cli.py
cds/config.py
cds/factory.py
cds/version.py
cds/wsgi.py
cds/modules/__init__.py
cds/modules/announcements/__init__.py
cds/modules/announcements/admin.py
cds/modules/announcements/models.py
cds/modules/announcements/views.py
cds/modules/announcements/alembic/028ba0bf5f85_creation_of_announcements_table.py
cds/modules/announcements/alembic/36f19890d4fd_create_announcements_branch.py
cds/modules/cds_iiif/__init__.py
cds/modules/cds_iiif/ext.py
cds/modules/cds_iiif/utils.py
cds/modules/deposit/__init__.py
cds/modules/deposit/api.py
cds/modules/deposit/bundles.py
cds/modules/deposit/errors.py
cds/modules/deposit/ext.py
cds/modules/deposit/facets.py
cds/modules/deposit/indexer.py
cds/modules/deposit/jsonresolver.py
cds/modules/deposit/links.py
cds/modules/deposit/receivers.py
cds/modules/deposit/resolver.py
cds/modules/deposit/search.py
cds/modules/deposit/tasks.py
cds/modules/deposit/views.py
cds/modules/deposit/loaders/__init__.py
cds/modules/deposit/loaders/loader.py
cds/modules/deposit/mappings/__init__.py
cds/modules/deposit/mappings/deposits/records/videos/project/project-v1.0.0.json
cds/modules/deposit/mappings/deposits/records/videos/video/video-v1.0.0.json
cds/modules/deposit/static/js/cds_deposit/main.js
cds/modules/deposit/static/js/cds_deposit/avc/avc.module.js
cds/modules/deposit/static/js/cds_deposit/avc/components/cdsActions.js
cds/modules/deposit/static/js/cds_deposit/avc/components/cdsDeposit.js
