Metadata-Version: 2.1
Name: CDS
Version: 1.0.1
Summary: Access articles, reports and multimedia content in HEP
Home-page: http://cds.cern.ch/
Author: CERN
Author-email: cds.support@cern.ch
License: GPLv3
Platform: any
Classifier: Environment :: Web Environment
Classifier: Intended Audience :: Developers
Classifier: License :: OSI Approved :: GNU General Public License v2 (GPLv2)
Classifier: Operating System :: OS Independent
Classifier: Programming Language :: Python
Classifier: Topic :: Internet :: WWW/HTTP :: Dynamic Content
Classifier: Topic :: Software Development :: Libraries :: Python Modules
Classifier: Programming Language :: Python :: 2
Classifier: Programming Language :: Python :: 2.7
Classifier: Programming Language :: Python :: 3
Classifier: Programming Language :: Python :: 3.5
Classifier: Development Status :: 2 - Pre-Alpha
Provides-Extra: all
Provides-Extra: docs
Provides-Extra: xrootd
Provides-Extra: tests
